zwpy2js.py
zwpy2js-0.1.0.dist-info/LICENSE.txt
zwpy2js-0.1.0.dist-info/METADATA
zwpy2js-0.1.0.dist-info/WHEEL
zwpy2js-0.1.0.dist-info/top_level.txt
zwpy2js-0.1.0.dist-info/RECORD
